__about__.py
flask_dogstatsd.py
setup.py
Flask_DogStatsd.egg-info/PKG-INFO
Flask_DogStatsd.egg-info/SOURCES.txt
Flask_DogStatsd.egg-info/dependency_links.txt
Flask_DogStatsd.egg-info/not-zip-safe
Flask_DogStatsd.egg-info/requires.txt
Flask_DogStatsd.egg-info/top_level.txt