Metadata-Version: 1.1
Name: Flask-DogStatsd
Version: 0.5.0
Summary: A Flask extension for dogstatsd-python
Home-page: https://github.com/xsleonard/flask-dogstatsd
Author: Steve Leonard
Author-email: sleonard76@gmail.com
License: MIT
Platform: any
Classifier: Intended Audience :: Developers
Classifier: License :: OSI Approved :: MIT License
Classifier: Operating System :: OS Independent
Classifier: Topic :: Software Development :: Libraries :: Python Modules
Classifier: Programming Language :: Python
